read-config/LICENSE
read-config/README.md
read-config/__init__.py
read-config/read_config.py
read-config/requirements.txt
readconfig/LICENSE
readconfig/README.md
readconfig/__init__.py
readconfig/read_config.py
readconfig/requirements.txt
readconfig-0.0.6.dist-info/METADATA
readconfig-0.0.6.dist-info/WHEEL
readconfig-0.0.6.dist-info/top_level.txt
readconfig-0.0.6.dist-info/RECORD
